{
  "meta": {
    "festival": "tomorrowland",
    "year": 2026,
    "weekend": "UNKNOWN",
    "createdAt": "2026-07-21T08:43:10.192Z",
    "source": "belgium.tomorrowland.com (playwright)",
    "version": 1
  },
  "slots": [
    {
      "weekend": "UNKNOWN",
      "date": "2026-07-16",
      "stage": "THE GATHERING",
      "start": "2026-07-16 13:00:00+02:00",
      "end": "2026-07-16 14:00:01+02:00",
      "artist": "Dino",
      "artistNormalized": "dino",
      "artistId": "cf06b730ed9ccafe",
      "positionId": "49ef46d8e25767b1",
      "slotId": "bb02b5a4b4f56dc7",
      "tomorrowlandArtistId": "2651252621"
    },
    {
      "weekend": "UNKNOWN",
      "date": "2026-07-16",
      "stage": "THE GATHERING",
      "start": "2026-07-16 14:00:00+02:00",
      "end": "2026-07-16 15:00:01+02:00",
      "artist": "Luna & Lenthe",
      "artistNormalized": "luna & lenthe",
      "artistId": "97e82c937e803081",
      "positionId": "0f970861977eff65",
      "slotId": "d2cb0c64918217a0",
      "tomorrowlandArtistId": "1536162340"
    },
    {
      "weekend": "UNKNOWN",
      "date": "2026-07-16",
      "stage": "THE GATHERING",
      "start": "2026-07-16 15:00:00+02:00",
      "end": "2026-07-16 16:00:01+02:00",
      "artist": "Lennert Wolfs",
      "artistNormalized": "lennert wolfs",
      "artistId": "3d69497643e3a17a",
      "positionId": "52232a17ea1f29cb",
      "slotId": "ed78c7f658749c13",
      "tomorrowlandArtistId": "1391236765"
    },
    {
      "weekend": "UNKNOWN",
      "date": "2026-07-16",
      "stage": "THE GATHERING",
      "start": "2026-07-16 16:00:00+02:00",
      "end": "2026-07-16 16:45:01+02:00",
      "artist": "Flavour Drop",
      "artistNormalized": "flavour drop",
      "artistId": "5a6ac8a37823d847",
      "positionId": "db5cb1cc6d8ea3ef",
      "slotId": "3a1bee783c8ecb93",
      "tomorrowlandArtistId": "1536101320"
    },
    {
      "weekend": "UNKNOWN",
      "date": "2026-07-16",
      "stage": "THE GATHERING",
      "start": "2026-07-16 16:45:00+02:00",
      "end": "2026-07-16 17:45:01+02:00",
      "artist": "Alycia Bezgo b2b Portex",
      "artistNormalized": "alycia bezgo b2b portex",
      "artistId": "1b6085e821a28eea",
      "positionId": "ce3cd1bb0387fff2",
      "slotId": "90a76d8b8923c0df"
    },
    {
      "weekend": "UNKNOWN",
      "date": "2026-07-16",
      "stage": "THE GATHERING",
      "start": "2026-07-16 17:45:00+02:00",
      "end": "2026-07-16 18:30:01+02:00",
      "artist": "5NAPBACK b2b Karakals",
      "artistNormalized": "5napback b2b karakals",
      "artistId": "6aee5f365639b265",
      "positionId": "660b5d6e39bc78c1",
      "slotId": "e903646762325340"
    },
    {
      "weekend": "UNKNOWN",
      "date": "2026-07-16",
      "stage": "THE GATHERING",
      "start": "2026-07-16 18:30:00+02:00",
      "end": "2026-07-16 19:30:01+02:00",
      "artist": "Amber Broos",
      "artistNormalized": "amber broos",
      "artistId": "a5fc998f3f97a467",
      "positionId": "a37097f4f4076c18",
      "slotId": "303317738befb7fa",
      "tomorrowlandArtistId": "1262705755"
    },
    {
      "weekend": "UNKNOWN",
      "date": "2026-07-16",
      "stage": "THE GATHERING",
      "start": "2026-07-16 19:30:00+02:00",
      "end": "2026-07-16 20:15:01+02:00",
      "artist": "Henri PFR",
      "artistNormalized": "henri pfr",
      "artistId": "f6fae09ddf3ef7f3",
      "positionId": "1bceccd4334ddbf9",
      "slotId": "1e2df59f68dee56b",
      "tomorrowlandArtistId": "1262703272"
    },
    {
      "weekend": "UNKNOWN",
      "date": "2026-07-16",
      "stage": "THE GATHERING",
      "start": "2026-07-16 20:15:00+02:00",
      "end": "2026-07-16 21:00:01+02:00",
      "artist": "Mark With A K & MC Chucky: Classics Set",
      "artistNormalized": "mark with a k & mc chucky: classics set",
      "artistId": "989540c086cd0c32",
      "positionId": "91f95cdefd451905",
      "slotId": "8564d5d35e8ddc8b"
    },
    {
      "weekend": "UNKNOWN",
      "date": "2026-07-16",
      "stage": "THE GATHERING",
      "start": "2026-07-16 21:00:00+02:00",
      "end": "2026-07-16 22:00:01+02:00",
      "artist": "SURPRISE",
      "artistNormalized": "surprise",
      "artistId": "3d9bb08573d8c465",
      "positionId": "09b645155d682d7a",
      "slotId": "a712b8bf5fc316c0",
      "tomorrowlandArtistId": "1272758908"
    },
    {
      "weekend": "UNKNOWN",
      "date": "2026-07-16",
      "stage": "THE GATHERING",
      "start": "2026-07-16 22:00:00+02:00",
      "end": "2026-07-16 23:00:01+02:00",
      "artist": "NO SURPRISE",
      "artistNormalized": "no surprise",
      "artistId": "526df6d1162d038f",
      "positionId": "a2bf3784a775a22c",
      "slotId": "5131d7348204b13a",
      "tomorrowlandArtistId": "1576037997"
    },
    {
      "weekend": "UNKNOWN",
      "date": "2026-07-16",
      "stage": "THE GATHERING",
      "start": "2026-07-16 23:00:00+02:00",
      "end": "2026-07-17 00:00:01+02:00",
      "artist": "SURPRISE",
      "artistNormalized": "surprise",
      "artistId": "3d9bb08573d8c465",
      "positionId": "73ac74b328823240",
      "slotId": "113ae123b7988c86",
      "tomorrowlandArtistId": "1272758908"
    },
    {
      "weekend": "UNKNOWN",
      "date": "2026-07-16",
      "stage": "THE GATHERING II",
      "start": "2026-07-16 14:00:00+02:00",
      "end": "2026-07-16 16:00:01+02:00",
      "artist": "ARTEN",
      "artistNormalized": "arten",
      "artistId": "c589c64619482600",
      "positionId": "81917d5ed3d5277b",
      "slotId": "1662ac3aec6c28ae",
      "tomorrowlandArtistId": "1397177066"
    },
    {
      "weekend": "UNKNOWN",
      "date": "2026-07-16",
      "stage": "THE GATHERING II",
      "start": "2026-07-16 16:00:00+02:00",
      "end": "2026-07-16 18:00:01+02:00",
      "artist": "BLUSHxBLUSH",
      "artistNormalized": "blushxblush",
      "artistId": "fee62dd3125263e3",
      "positionId": "d53287d1dc3d6b39",
      "slotId": "5fe20763bafa5726",
      "tomorrowlandArtistId": "1977203905"
    },
    {
      "weekend": "UNKNOWN",
      "date": "2026-07-16",
      "stage": "THE GATHERING II",
      "start": "2026-07-16 18:00:00+02:00",
      "end": "2026-07-16 20:00:01+02:00",
      "artist": "Prinz",
      "artistNormalized": "prinz",
      "artistId": "e4406856ccd25f33",
      "positionId": "f9de03caf6a80b71",
      "slotId": "f47adb2d1b447eb8",
      "tomorrowlandArtistId": "1576010712"
    },
    {
      "weekend": "UNKNOWN",
      "date": "2026-07-16",
      "stage": "THE GATHERING II",
      "start": "2026-07-16 20:00:00+02:00",
      "end": "2026-07-16 22:00:01+02:00",
      "artist": "Camila Jun",
      "artistNormalized": "camila jun",
      "artistId": "1c9b1563cca0c08f",
      "positionId": "97bf24e0e0d5a404",
      "slotId": "4db21a7ba7f15bd1",
      "tomorrowlandArtistId": "1893969378"
    },
    {
      "weekend": "UNKNOWN",
      "date": "2026-07-16",
      "stage": "THE GATHERING II",
      "start": "2026-07-16 22:00:00+02:00",
      "end": "2026-07-17 00:00:01+02:00",
      "artist": "NOSI",
      "artistNormalized": "nosi",
      "artistId": "46abd8ed192cbd06",
      "positionId": "ce3c2e6f2f57a361",
      "slotId": "0f168fab30c5b5bf",
      "tomorrowlandArtistId": "1938375508"
    },
    {
      "weekend": "UNKNOWN",
      "date": "2026-07-23",
      "stage": "THE GATHERING",
      "start": "2026-07-23 13:00:00+02:00",
      "end": "2026-07-23 14:00:01+02:00",
      "artist": "Renee",
      "artistNormalized": "renee",
      "artistId": "558fd581298a843b",
      "positionId": "3ad0df4e2237d713",
      "slotId": "83d6011147837f4f"
    },
    {
      "weekend": "UNKNOWN",
      "date": "2026-07-23",
      "stage": "THE GATHERING",
      "start": "2026-07-23 14:00:00+02:00",
      "end": "2026-07-23 15:00:01+02:00",
      "artist": "Naomi Cazier",
      "artistNormalized": "naomi cazier",
      "artistId": "a5391698b1433114",
      "positionId": "c8a0897a9a4cdcbd",
      "slotId": "9c1fda466d736c99"
    },
    {
      "weekend": "UNKNOWN",
      "date": "2026-07-23",
      "stage": "THE GATHERING",
      "start": "2026-07-23 15:00:00+02:00",
      "end": "2026-07-23 16:00:01+02:00",
      "artist": "Dave Lambert",
      "artistNormalized": "dave lambert",
      "artistId": "9dc48c659debb3d0",
      "positionId": "47cb92fa74edac1c",
      "slotId": "5c7753cad9b4a26f",
      "tomorrowlandArtistId": "1532641763"
    },
    {
      "weekend": "UNKNOWN",
      "date": "2026-07-23",
      "stage": "THE GATHERING",
      "start": "2026-07-23 16:00:00+02:00",
      "end": "2026-07-23 16:45:01+02:00",
      "artist": "Meaghan",
      "artistNormalized": "meaghan",
      "artistId": "eb119c6b74cd1768",
      "positionId": "1e6c39a07cef9ce5",
      "slotId": "2d45d20bec00566d"
    },
    {
      "weekend": "UNKNOWN",
      "date": "2026-07-23",
      "stage": "THE GATHERING",
      "start": "2026-07-23 16:45:00+02:00",
      "end": "2026-07-23 17:30:01+02:00",
      "artist": "ELFIGO",
      "artistNormalized": "elfigo",
      "artistId": "28a3a4d078f10135",
      "positionId": "afdd8b7d9da1ef69",
      "slotId": "e47695e80e771edd",
      "tomorrowlandArtistId": "1568023510"
    },
    {
      "weekend": "UNKNOWN",
      "date": "2026-07-23",
      "stage": "THE GATHERING",
      "start": "2026-07-23 17:30:00+02:00",
      "end": "2026-07-23 18:15:01+02:00",
      "artist": "BYORN",
      "artistNormalized": "byorn",
      "artistId": "00e33fe67591dea8",
      "positionId": "b18e26bbdd31286d",
      "slotId": "59923e526242ab6e",
      "tomorrowlandArtistId": "1938176528"
    },
    {
      "weekend": "UNKNOWN",
      "date": "2026-07-23",
      "stage": "THE GATHERING",
      "start": "2026-07-23 18:15:00+02:00",
      "end": "2026-07-23 19:15:01+02:00",
      "artist": "Omdat Het Kan & Average Rob",
      "artistNormalized": "omdat het kan & average rob",
      "artistId": "8d0541c76d2f0727",
      "positionId": "311c9de061913e99",
      "slotId": "ccc5e45fcbbc9918",
      "tomorrowlandArtistId": "1297368615"
    },
    {
      "weekend": "UNKNOWN",
      "date": "2026-07-23",
      "stage": "THE GATHERING",
      "start": "2026-07-23 19:15:00+02:00",
      "end": "2026-07-23 20:15:01+02:00",
      "artist": "Regi b2b Yves V",
      "artistNormalized": "regi b2b yves v",
      "artistId": "a5036f6c47837630",
      "positionId": "5cf6052b618e5d03",
      "slotId": "d922cec36fc903fb"
    },
    {
      "weekend": "UNKNOWN",
      "date": "2026-07-23",
      "stage": "THE GATHERING",
      "start": "2026-07-23 20:15:00+02:00",
      "end": "2026-07-23 21:00:01+02:00",
      "artist": "Andromedik",
      "artistNormalized": "andromedik",
      "artistId": "b8cad92b72d6b80e",
      "positionId": "5002482c16d9d403",
      "slotId": "bf099db443b7eb13",
      "tomorrowlandArtistId": "1262708699"
    },
    {
      "weekend": "UNKNOWN",
      "date": "2026-07-23",
      "stage": "THE GATHERING",
      "start": "2026-07-23 21:00:00+02:00",
      "end": "2026-07-23 22:00:01+02:00",
      "artist": "SURPRISE",
      "artistNormalized": "surprise",
      "artistId": "3d9bb08573d8c465",
      "positionId": "770f524356fa0e9c",
      "slotId": "91f2a48e368acec6",
      "tomorrowlandArtistId": "1272758908"
    },
    {
      "weekend": "UNKNOWN",
      "date": "2026-07-23",
      "stage": "THE GATHERING",
      "start": "2026-07-23 22:00:00+02:00",
      "end": "2026-07-23 23:00:01+02:00",
      "artist": "SURPRISE",
      "artistNormalized": "surprise",
      "artistId": "3d9bb08573d8c465",
      "positionId": "15b2281efebadc6b",
      "slotId": "88c5a47fe8dca566",
      "tomorrowlandArtistId": "1272758908"
    },
    {
      "weekend": "UNKNOWN",
      "date": "2026-07-23",
      "stage": "THE GATHERING",
      "start": "2026-07-23 23:00:00+02:00",
      "end": "2026-07-24 00:00:01+02:00",
      "artist": "SURPRISE",
      "artistNormalized": "surprise",
      "artistId": "3d9bb08573d8c465",
      "positionId": "ef5ae7b49418be39",
      "slotId": "d693476dad272b01",
      "tomorrowlandArtistId": "1272758908"
    },
    {
      "weekend": "UNKNOWN",
      "date": "2026-07-23",
      "stage": "THE GATHERING II",
      "start": "2026-07-23 14:00:00+02:00",
      "end": "2026-07-23 16:00:01+02:00",
      "artist": "MAEYER",
      "artistNormalized": "maeyer",
      "artistId": "6b07d5b3e05b052d",
      "positionId": "df3145f579a9ebf9",
      "slotId": "82ff4ed7a677d2e7"
    },
    {
      "weekend": "UNKNOWN",
      "date": "2026-07-23",
      "stage": "THE GATHERING II",
      "start": "2026-07-23 16:00:00+02:00",
      "end": "2026-07-23 18:00:01+02:00",
      "artist": "Billy",
      "artistNormalized": "billy",
      "artistId": "a19da73af96608ab",
      "positionId": "45d57708eeb9b23b",
      "slotId": "7f5298d23b2f44de"
    },
    {
      "weekend": "UNKNOWN",
      "date": "2026-07-23",
      "stage": "THE GATHERING II",
      "start": "2026-07-23 18:00:00+02:00",
      "end": "2026-07-23 20:00:01+02:00",
      "artist": "Bisoux",
      "artistNormalized": "bisoux",
      "artistId": "5ed351e4b0cec759",
      "positionId": "a4072b19cbab0d77",
      "slotId": "c3fa94ceae57f22f",
      "tomorrowlandArtistId": "1957408500"
    },
    {
      "weekend": "UNKNOWN",
      "date": "2026-07-23",
      "stage": "THE GATHERING II",
      "start": "2026-07-23 20:00:00+02:00",
      "end": "2026-07-23 22:00:01+02:00",
      "artist": "ROW1",
      "artistNormalized": "row1",
      "artistId": "a308a44eb8b4787a",
      "positionId": "7a020c6f6e184dd8",
      "slotId": "4b624408e9d52f55",
      "tomorrowlandArtistId": "1809934851"
    },
    {
      "weekend": "UNKNOWN",
      "date": "2026-07-23",
      "stage": "THE GATHERING II",
      "start": "2026-07-23 22:00:00+02:00",
      "end": "2026-07-24 00:00:01+02:00",
      "artist": "Luna Fields",
      "artistNormalized": "luna fields",
      "artistId": "4429fc6470722d2d",
      "positionId": "acec8e801497c60f",
      "slotId": "2361898e7a49ce74",
      "tomorrowlandArtistId": "1790357496"
    }
  ]
}
