{
  "meta": {
    "createdAt": "2026-06-23T10:02:38.386Z",
    "version": 1,
    "note": "latest changes per weekend"
  },
  "latest": {
    "W1": {
      "meta": {
        "weekend": "W1",
        "from": "20260622_122510Z_W1.json",
        "to": "20260623_100208Z_W1.json",
        "createdAt": "2026-06-23T10:02:38.386Z",
        "version": 1
      },
      "summary": {
        "added": 0,
        "removed": 0,
        "replaced": 0
      },
      "added": [],
      "removed": [],
      "replaced": []
    },
    "W2": {
      "meta": {
        "weekend": "W2",
        "from": "20260622_122510Z_W2.json",
        "to": "20260623_100208Z_W2.json",
        "createdAt": "2026-06-23T10:02:38.386Z",
        "version": 1
      },
      "summary": {
        "added": 0,
        "removed": 0,
        "replaced": 0
      },
      "added": [],
      "removed": [],
      "replaced": []
    }
  }
}
